lucit_licensing_python/__init__.cp38-win32.pyd
lucit_licensing_python/cli.cp38-win32.pyd
lucit_licensing_python/exceptions.cp38-win32.pyd
lucit_licensing_python/manager.cp38-win32.pyd
lucit_licensing_python-1.8.2.dist-info/LICENSE
lucit_licensing_python-1.8.2.dist-info/METADATA
lucit_licensing_python-1.8.2.dist-info/WHEEL
lucit_licensing_python-1.8.2.dist-info/entry_points.txt
lucit_licensing_python-1.8.2.dist-info/top_level.txt
lucit_licensing_python-1.8.2.dist-info/RECORD
