Metadata-Version: 2.1
Name: lucit-licensing-python
Version: 1.8.2
Summary: LUCIT Licensing Client Module
Home-page: https://github.com/LUCIT-Systems-and-Development/lucit-licensing-python
Author: LUCIT Systems and Development
Author-email: info@lucit.tech
License: LSOSL - LUCIT Synergetic Open Source License
Project-URL: Documentation, https://lucit-licensing-python.docs.lucit.tech
Project-URL: Wiki, https://github.com/LUCIT-Systems-and-Development/lucit-licensing-python/wiki
Project-URL: Author, https://www.lucit.tech
Project-URL: Changes, https://lucit-licensing-python.docs.lucit.tech/changelog.html
Project-URL: License, https://lucit-licensing-python.docs.lucit.tech/license.html
Project-URL: Issue Tracker, https://github.com/LUCIT-Systems-and-Development/lucit-licensing-python/issues
Project-URL: Telegram, https://t.me/unicorndevs
Project-URL: Chat, https://app.gitter.im/#/room/#lucit-licensing-python:gitter.im
Project-URL: Get Support, https://www.lucit.tech/get-support.html
Project-URL: LUCIT Online Shop, https://shop.lucit.services/software
Classifier: Development Status :: 5 - Production/Stable
Classifier: Programming Language :: Python :: 3.7
Classifier: Programming Language :: Python :: 3.8
Classifier: Programming Language :: Python :: 3.9
Classifier: Programming Language :: Python :: 3.10
Classifier: Programming Language :: Python :: 3.11
Classifier: Programming Language :: Python :: 3.12
Classifier: License :: Other/Proprietary License
Classifier: Intended Audience :: Developers
Classifier: Operating System :: OS Independent
Classifier: Topic :: Software Development :: Libraries :: Python Modules
Requires-Python: >=3.7.0
License-File: LICENSE
Requires-Dist: Cython
Requires-Dist: requests
Requires-Dist: simplejson
